click_completion_dyncomplete/__init__.py
click_completion_dyncomplete/bash.j2
click_completion_dyncomplete/core.py
click_completion_dyncomplete/fish.j2
click_completion_dyncomplete/lib.py
click_completion_dyncomplete/patch.py
click_completion_dyncomplete/powershell.j2
click_completion_dyncomplete/zsh.j2
click_completion_dyncomplete-0.5.2.1.dist-info/LICENSE
click_completion_dyncomplete-0.5.2.1.dist-info/METADATA
click_completion_dyncomplete-0.5.2.1.dist-info/WHEEL
click_completion_dyncomplete-0.5.2.1.dist-info/top_level.txt
click_completion_dyncomplete-0.5.2.1.dist-info/RECORD
