Metadata-Version: 2.1
Name: click-completion-dyncomplete
Version: 0.5.2.1
Summary: Fish, Bash, Zsh and PowerShell completion for Click
Home-page: https://github.com/Kotaimen/click-completion
Author: Gaëtan Lehmann
Author-email: gaetan.lehmann@gmail.com
License: MIT
Platform: UNKNOWN
Requires-Dist: click
Requires-Dist: jinja2
Requires-Dist: six
Requires-Dist: shellingham
Requires-Dist: enum34 ; python_version < "3"
